[
  { "merk": "VOLVO", "model": "XC90 T8", "rdwHandelsbenaming": "XC90 T8 Twin Engine", "bouwjaarVanaf": 2015, "bouwjaarTot": 2019, "type": "PHEV", "batterijKwh": 10.4, "bruikbaarKwh": 9.2, "laadVermogenAcKw": 3.7, "elektrischBereikKm": 40 },
  { "merk": "VOLVO", "model": "XC90 T8", "rdwHandelsbenaming": "XC90 T8 Twin Engine", "bouwjaarVanaf": 2020, "bouwjaarTot": 2024, "type": "PHEV", "batterijKwh": 11.6, "bruikbaarKwh": 10.4, "laadVermogenAcKw": 3.7, "elektrischBereikKm": 40 },
  { "merk": "VOLVO", "model": "XC60 T8", "rdwHandelsbenaming": "XC60 T8 Twin Engine", "bouwjaarVanaf": 2018, "bouwjaarTot": 2021, "type": "PHEV", "batterijKwh": 11.6, "bruikbaarKwh": 10.4, "laadVermogenAcKw": 3.7, "elektrischBereikKm": 45 },
  { "merk": "VOLVO", "model": "XC60 T8", "rdwHandelsbenaming": "XC60 T8 Recharge", "bouwjaarVanaf": 2022, "bouwjaarTot": 2024, "type": "PHEV", "batterijKwh": 18.8, "bruikbaarKwh": 17.3, "laadVermogenAcKw": 6.4, "elektrischBereikKm": 81 },
  { "merk": "VOLVO", "model": "V60 T8", "rdwHandelsbenaming": "V60 T8 Twin Engine", "bouwjaarVanaf": 2019, "bouwjaarTot": 2021, "type": "PHEV", "batterijKwh": 11.6, "bruikbaarKwh": 10.4, "laadVermogenAcKw": 3.7, "elektrischBereikKm": 45 },
  { "merk": "VOLVO", "model": "XC40 Recharge", "rdwHandelsbenaming": "XC40 RECHARGE", "bouwjaarVanaf": 2021, "bouwjaarTot": 2022, "type": "BEV", "batterijKwh": 78.0, "bruikbaarKwh": 75.0, "laadVermogenAcKw": 11.0, "laadVermogenDcKw": 150, "elektrischBereikKm": 418 },
  { "merk": "VOLVO", "model": "XC40 Recharge", "rdwHandelsbenaming": "XC40 RECHARGE", "bouwjaarVanaf": 2023, "bouwjaarTot": 2025, "type": "BEV", "batterijKwh": 82.0, "bruikbaarKwh": 79.0, "laadVermogenAcKw": 11.0, "laadVermogenDcKw": 200, "elektrischBereikKm": 460 },
  { "merk": "VOLVO", "model": "EX30", "rdwHandelsbenaming": "EX30", "bouwjaarVanaf": 2023, "bouwjaarTot": 2025, "type": "BEV", "batterijKwh": 51.0, "bruikbaarKwh": 49.0, "laadVermogenAcKw": 11.0, "laadVermogenDcKw": 153, "elektrischBereikKm": 344 },
  { "merk": "TESLA", "model": "Model Y", "rdwHandelsbenaming": "MODEL Y", "bouwjaarVanaf": 2021, "bouwjaarTot": 2025, "type": "BEV", "batterijKwh": 75.0, "bruikbaarKwh": 72.0, "laadVermogenAcKw": 11.0, "laadVermogenDcKw": 250, "elektrischBereikKm": 533 },
  { "merk": "TESLA", "model": "Model 3", "rdwHandelsbenaming": "MODEL 3", "bouwjaarVanaf": 2019, "bouwjaarTot": 2025, "type": "BEV", "batterijKwh": 75.0, "bruikbaarKwh": 72.0, "laadVermogenAcKw": 11.0, "laadVermogenDcKw": 170, "elektrischBereikKm": 491 },
  { "merk": "FORD", "model": "Kuga PHEV", "rdwHandelsbenaming": "KUGA", "bouwjaarVanaf": 2020, "bouwjaarTot": 2022, "type": "PHEV", "batterijKwh": 14.4, "bruikbaarKwh": 13.6, "laadVermogenAcKw": 3.7, "elektrischBereikKm": 56 },
  { "merk": "FORD", "model": "Kuga PHEV", "rdwHandelsbenaming": "KUGA", "bouwjaarVanaf": 2023, "bouwjaarTot": 2025, "type": "PHEV", "batterijKwh": 14.4, "bruikbaarKwh": 13.6, "laadVermogenAcKw": 3.7, "elektrischBereikKm": 69 },
  { "merk": "VOLKSWAGEN", "model": "Golf GTE", "rdwHandelsbenaming": "GOLF", "bouwjaarVanaf": 2020, "bouwjaarTot": 2024, "type": "PHEV", "batterijKwh": 13.0, "bruikbaarKwh": 12.0, "laadVermogenAcKw": 3.6, "elektrischBereikKm": 60 },
  { "merk": "VOLKSWAGEN", "model": "Passat GTE", "rdwHandelsbenaming": "PASSAT", "bouwjaarVanaf": 2019, "bouwjaarTot": 2023, "type": "PHEV", "batterijKwh": 13.0, "bruikbaarKwh": 12.0, "laadVermogenAcKw": 3.6, "elektrischBereikKm": 55 },
  { "merk": "VOLKSWAGEN", "model": "Tiguan eHybrid", "rdwHandelsbenaming": "TIGUAN", "bouwjaarVanaf": 2021, "bouwjaarTot": 2024, "type": "PHEV", "batterijKwh": 13.0, "bruikbaarKwh": 12.0, "laadVermogenAcKw": 3.6, "elektrischBereikKm": 50 },
  { "merk": "VOLKSWAGEN", "model": "ID.4", "rdwHandelsbenaming": "ID.4", "bouwjaarVanaf": 2021, "bouwjaarTot": 2022, "type": "BEV", "batterijKwh": 77.0, "bruikbaarKwh": 74.0, "laadVermogenAcKw": 11.0, "laadVermogenDcKw": 135, "elektrischBereikKm": 520 },
  { "merk": "VOLKSWAGEN", "model": "ID.4", "rdwHandelsbenaming": "ID.4", "bouwjaarVanaf": 2023, "bouwjaarTot": 2025, "type": "BEV", "batterijKwh": 82.0, "bruikbaarKwh": 79.0, "laadVermogenAcKw": 11.0, "laadVermogenDcKw": 175, "elektrischBereikKm": 522 },
  { "merk": "BMW", "model": "330e", "rdwHandelsbenaming": "330E", "bouwjaarVanaf": 2019, "bouwjaarTot": 2024, "type": "PHEV", "batterijKwh": 12.0, "bruikbaarKwh": 11.0, "laadVermogenAcKw": 3.7, "elektrischBereikKm": 60 },
  { "merk": "BMW", "model": "530e", "rdwHandelsbenaming": "530E", "bouwjaarVanaf": 2019, "bouwjaarTot": 2024, "type": "PHEV", "batterijKwh": 12.0, "bruikbaarKwh": 11.0, "laadVermogenAcKw": 3.7, "elektrischBereikKm": 54 },
  { "merk": "BMW", "model": "X5 45e", "rdwHandelsbenaming": "X5", "bouwjaarVanaf": 2019, "bouwjaarTot": 2024, "type": "PHEV", "batterijKwh": 24.0, "bruikbaarKwh": 21.6, "laadVermogenAcKw": 3.7, "elektrischBereikKm": 87 },
  { "merk": "MERCEDES-BENZ", "model": "C 300 e", "rdwHandelsbenaming": "C 300 E", "bouwjaarVanaf": 2021, "bouwjaarTot": 2025, "type": "PHEV", "batterijKwh": 25.4, "bruikbaarKwh": 23.0, "laadVermogenAcKw": 11.0, "elektrischBereikKm": 111 },
  { "merk": "MERCEDES-BENZ", "model": "E 300 e", "rdwHandelsbenaming": "E 300 E", "bouwjaarVanaf": 2019, "bouwjaarTot": 2023, "type": "PHEV", "batterijKwh": 13.5, "bruikbaarKwh": 12.0, "laadVermogenAcKw": 7.4, "elektrischBereikKm": 52 },
  { "merk": "MERCEDES-BENZ", "model": "GLC 300 e", "rdwHandelsbenaming": "GLC 300 E", "bouwjaarVanaf": 2022, "bouwjaarTot": 2025, "type": "PHEV", "batterijKwh": 31.2, "bruikbaarKwh": 28.6, "laadVermogenAcKw": 11.0, "elektrischBereikKm": 120 },
  { "merk": "AUDI", "model": "A3 45 TFSI e", "rdwHandelsbenaming": "A3", "bouwjaarVanaf": 2021, "bouwjaarTot": 2024, "type": "PHEV", "batterijKwh": 13.0, "bruikbaarKwh": 12.0, "laadVermogenAcKw": 3.6, "elektrischBereikKm": 62 },
  { "merk": "AUDI", "model": "A6 55 TFSI e", "rdwHandelsbenaming": "A6", "bouwjaarVanaf": 2019, "bouwjaarTot": 2024, "type": "PHEV", "batterijKwh": 14.1, "bruikbaarKwh": 12.7, "laadVermogenAcKw": 7.4, "elektrischBereikKm": 51 },
  { "merk": "AUDI", "model": "Q5 55 TFSI e", "rdwHandelsbenaming": "Q5", "bouwjaarVanaf": 2019, "bouwjaarTot": 2024, "type": "PHEV", "batterijKwh": 14.1, "bruikbaarKwh": 12.7, "laadVermogenAcKw": 7.4, "elektrischBereikKm": 43 },
  { "merk": "MITSUBISHI", "model": "Outlander PHEV", "rdwHandelsbenaming": "OUTLANDER", "bouwjaarVanaf": 2013, "bouwjaarTot": 2021, "type": "PHEV", "batterijKwh": 13.8, "bruikbaarKwh": 12.0, "laadVermogenAcKw": 3.7, "elektrischBereikKm": 55 },
  { "merk": "MITSUBISHI", "model": "Outlander PHEV", "rdwHandelsbenaming": "OUTLANDER", "bouwjaarVanaf": 2022, "bouwjaarTot": 2025, "type": "PHEV", "batterijKwh": 20.0, "bruikbaarKwh": 18.0, "laadVermogenAcKw": 6.0, "elektrischBereikKm": 83 },
  { "merk": "KIA", "model": "Niro PHEV", "rdwHandelsbenaming": "NIRO", "bouwjaarVanaf": 2017, "bouwjaarTot": 2021, "type": "PHEV", "batterijKwh": 8.9, "bruikbaarKwh": 7.9, "laadVermogenAcKw": 3.3, "elektrischBereikKm": 58 },
  { "merk": "KIA", "model": "Niro PHEV", "rdwHandelsbenaming": "NIRO", "bouwjaarVanaf": 2022, "bouwjaarTot": 2025, "type": "PHEV", "batterijKwh": 11.1, "bruikbaarKwh": 9.8, "laadVermogenAcKw": 3.6, "elektrischBereikKm": 65 },
  { "merk": "KIA", "model": "Niro EV", "rdwHandelsbenaming": "NIRO", "bouwjaarVanaf": 2022, "bouwjaarTot": 2025, "type": "BEV", "batterijKwh": 64.8, "bruikbaarKwh": 62.4, "laadVermogenAcKw": 11.0, "laadVermogenDcKw": 100, "elektrischBereikKm": 463 },
  { "merk": "KIA", "model": "EV6", "rdwHandelsbenaming": "EV6", "bouwjaarVanaf": 2022, "bouwjaarTot": 2025, "type": "BEV", "batterijKwh": 77.4, "bruikbaarKwh": 74.0, "laadVermogenAcKw": 11.0, "laadVermogenDcKw": 233, "elektrischBereikKm": 528 },
  { "merk": "HYUNDAI", "model": "Tucson PHEV", "rdwHandelsbenaming": "TUCSON", "bouwjaarVanaf": 2021, "bouwjaarTot": 2025, "type": "PHEV", "batterijKwh": 13.8, "bruikbaarKwh": 12.4, "laadVermogenAcKw": 7.2, "elektrischBereikKm": 62 },
  { "merk": "HYUNDAI", "model": "Ioniq 5", "rdwHandelsbenaming": "IONIQ 5", "bouwjaarVanaf": 2021, "bouwjaarTot": 2025, "type": "BEV", "batterijKwh": 77.4, "bruikbaarKwh": 74.0, "laadVermogenAcKw": 11.0, "laadVermogenDcKw": 233, "elektrischBereikKm": 507 },
  { "merk": "HYUNDAI", "model": "Ioniq 6", "rdwHandelsbenaming": "IONIQ 6", "bouwjaarVanaf": 2023, "bouwjaarTot": 2025, "type": "BEV", "batterijKwh": 77.4, "bruikbaarKwh": 74.0, "laadVermogenAcKw": 11.0, "laadVermogenDcKw": 233, "elektrischBereikKm": 614 },
  { "merk": "TOYOTA", "model": "RAV4 PHEV", "rdwHandelsbenaming": "RAV4", "bouwjaarVanaf": 2020, "bouwjaarTot": 2025, "type": "PHEV", "batterijKwh": 18.1, "bruikbaarKwh": 14.4, "laadVermogenAcKw": 3.3, "elektrischBereikKm": 75 },
  { "merk": "PEUGEOT", "model": "308 Hybrid", "rdwHandelsbenaming": "308", "bouwjaarVanaf": 2022, "bouwjaarTot": 2025, "type": "PHEV", "batterijKwh": 12.4, "bruikbaarKwh": 11.0, "laadVermogenAcKw": 3.7, "elektrischBereikKm": 60 },
  { "merk": "PEUGEOT", "model": "3008 Hybrid", "rdwHandelsbenaming": "3008", "bouwjaarVanaf": 2019, "bouwjaarTot": 2023, "type": "PHEV", "batterijKwh": 13.2, "bruikbaarKwh": 11.8, "laadVermogenAcKw": 3.7, "elektrischBereikKm": 56 },
  { "merk": "LAND ROVER", "model": "Range Rover P400e", "rdwHandelsbenaming": "RANGE ROVER", "bouwjaarVanaf": 2018, "bouwjaarTot": 2021, "type": "PHEV", "batterijKwh": 31.8, "bruikbaarKwh": 25.0, "laadVermogenAcKw": 7.2, "elektrischBereikKm": 88 },
  { "merk": "LAND ROVER", "model": "Range Rover P400e", "rdwHandelsbenaming": "RANGE ROVER", "bouwjaarVanaf": 2022, "bouwjaarTot": 2025, "type": "PHEV", "batterijKwh": 38.2, "bruikbaarKwh": 31.8, "laadVermogenAcKw": 7.2, "elektrischBereikKm": 113 },
  { "merk": "LAND ROVER", "model": "Range Rover Sport P400e", "rdwHandelsbenaming": "RANGE ROVER SPORT", "bouwjaarVanaf": 2018, "bouwjaarTot": 2022, "type": "PHEV", "batterijKwh": 31.8, "bruikbaarKwh": 25.0, "laadVermogenAcKw": 7.2, "elektrischBereikKm": 88 },
  { "merk": "PORSCHE", "model": "Cayenne E-Hybrid", "rdwHandelsbenaming": "CAYENNE", "bouwjaarVanaf": 2018, "bouwjaarTot": 2021, "type": "PHEV", "batterijKwh": 17.9, "bruikbaarKwh": 14.1, "laadVermogenAcKw": 7.2, "elektrischBereikKm": 44 },
  { "merk": "PORSCHE", "model": "Cayenne E-Hybrid", "rdwHandelsbenaming": "CAYENNE", "bouwjaarVanaf": 2022, "bouwjaarTot": 2025, "type": "PHEV", "batterijKwh": 25.9, "bruikbaarKwh": 21.8, "laadVermogenAcKw": 7.2, "elektrischBereikKm": 90 },
  { "merk": "PORSCHE", "model": "Panamera E-Hybrid", "rdwHandelsbenaming": "PANAMERA", "bouwjaarVanaf": 2017, "bouwjaarTot": 2025, "type": "PHEV", "batterijKwh": 17.9, "bruikbaarKwh": 14.1, "laadVermogenAcKw": 7.2, "elektrischBereikKm": 54 },
  { "merk": "SKODA", "model": "Octavia iV", "rdwHandelsbenaming": "OCTAVIA", "bouwjaarVanaf": 2021, "bouwjaarTot": 2025, "type": "PHEV", "batterijKwh": 13.0, "bruikbaarKwh": 12.0, "laadVermogenAcKw": 3.6, "elektrischBereikKm": 55 },
  { "merk": "OPEL", "model": "Grandland X PHEV", "rdwHandelsbenaming": "GRANDLAND", "bouwjaarVanaf": 2019, "bouwjaarTot": 2025, "type": "PHEV", "batterijKwh": 13.2, "bruikbaarKwh": 11.8, "laadVermogenAcKw": 3.7, "elektrischBereikKm": 56 },
  { "merk": "RENAULT", "model": "Megane E-Tech", "rdwHandelsbenaming": "MEGANE", "bouwjaarVanaf": 2022, "bouwjaarTot": 2025, "type": "BEV", "batterijKwh": 60.0, "bruikbaarKwh": 58.0, "laadVermogenAcKw": 11.0, "laadVermogenDcKw": 130, "elektrischBereikKm": 450 },
  { "merk": "NISSAN", "model": "Leaf", "rdwHandelsbenaming": "LEAF", "bouwjaarVanaf": 2018, "bouwjaarTot": 2021, "type": "BEV", "batterijKwh": 40.0, "bruikbaarKwh": 36.0, "laadVermogenAcKw": 6.6, "laadVermogenDcKw": 50, "elektrischBereikKm": 270 },
  { "merk": "NISSAN", "model": "Leaf e+", "rdwHandelsbenaming": "LEAF", "bouwjaarVanaf": 2019, "bouwjaarTot": 2023, "type": "BEV", "batterijKwh": 62.0, "bruikbaarKwh": 59.0, "laadVermogenAcKw": 6.6, "laadVermogenDcKw": 100, "elektrischBereikKm": 385 }
]
